sbo_service_inventory/__init__.py
sbo_service_inventory/inventory.py
sbo_service_inventory-0.1.3.dist-info/METADATA
sbo_service_inventory-0.1.3.dist-info/WHEEL
sbo_service_inventory-0.1.3.dist-info/top_level.txt
sbo_service_inventory-0.1.3.dist-info/RECORD
